odoo/addons/stock_picking_origin_reference_sale/README.rst
odoo/addons/stock_picking_origin_reference_sale/__init__.py
odoo/addons/stock_picking_origin_reference_sale/__manifest__.py
odoo/addons/stock_picking_origin_reference_sale/i18n/stock_picking_origin_reference_sale.pot
odoo/addons/stock_picking_origin_reference_sale/models/__init__.py
odoo/addons/stock_picking_origin_reference_sale/models/stock_picking.py
odoo/addons/stock_picking_origin_reference_sale/readme/CONTRIBUTORS.rst
odoo/addons/stock_picking_origin_reference_sale/readme/DESCRIPTION.rst
odoo/addons/stock_picking_origin_reference_sale/static/description/icon.png
odoo/addons/stock_picking_origin_reference_sale/static/description/index.html
odoo/addons/stock_picking_origin_reference_sale/tests/__init__.py
odoo/addons/stock_picking_origin_reference_sale/tests/test_stock_picking_origin_reference_sale.py
odoo13_addon_stock_picking_origin_reference_sale-13.0.1.0.1.dev4.dist-info/METADATA
odoo13_addon_stock_picking_origin_reference_sale-13.0.1.0.1.dev4.dist-info/WHEEL
odoo13_addon_stock_picking_origin_reference_sale-13.0.1.0.1.dev4.dist-info/top_level.txt
odoo13_addon_stock_picking_origin_reference_sale-13.0.1.0.1.dev4.dist-info/RECORD
